{
  "brand": "슬룸",
  "month": "2026-03",
  "generated_at": "",
  "source": "uncaptured_negative",
  "uncaptured_total": 59,
  "candidates": [
    {
      "word": "진동",
      "type": "improvement",
      "count": 35,
      "review_ids": [
        "89786",
        "96614",
        "96636",
        "89750",
        "96553",
        "96818",
        "89926",
        "96785",
        "89906",
        "89758",
        "96512",
        "96735",
        "89807",
        "96603",
        "96791",
        "89897",
        "96659",
        "96562",
        "89739",
        "89917",
        "96632",
        "89940",
        "96764",
        "96559",
        "96708",
        "96834",
        "96660",
        "89886",
        "96774",
        "96802",
        "96686",
        "89765",
        "96745",
        "96825",
        "89810"
      ],
      "samples": []
    },
    {
      "word": "품질/성능",
      "type": "complaint",
      "count": 19,
      "review_ids": [
        "96614",
        "96636",
        "96553",
        "89931",
        "89782",
        "96512",
        "96735",
        "96659",
        "89857",
        "96632",
        "89940",
        "89898",
        "96764",
        "96559",
        "96708",
        "96660",
        "96774",
        "96802",
        "96745"
      ],
      "samples": []
    },
    {
      "word": "소리",
      "type": "complaint",
      "count": 17,
      "review_ids": [
        "96636",
        "89750",
        "96818",
        "89926",
        "89782",
        "96512",
        "96551",
        "96562",
        "89739",
        "89867",
        "96632",
        "89940",
        "96764",
        "89886",
        "96686",
        "96745",
        "89810"
      ],
      "samples": []
    },
    {
      "word": "기능/모드",
      "type": "improvement",
      "count": 15,
      "review_ids": [
        "96764",
        "89786",
        "96559",
        "96614",
        "96636",
        "96553",
        "96708",
        "96667",
        "96774",
        "89917",
        "96540",
        "89779",
        "89897",
        "96745",
        "89810"
      ],
      "samples": []
    },
    {
      "word": "크기/사이즈",
      "type": "complaint",
      "count": 5,
      "review_ids": [
        "96764",
        "89765",
        "96551",
        "96659",
        "89761"
      ],
      "samples": []
    },
    {
      "word": "충전",
      "type": "complaint",
      "count": 5,
      "review_ids": [
        "89786",
        "96559",
        "96660",
        "96802",
        "89898"
      ],
      "samples": []
    },
    {
      "word": "배송",
      "type": "complaint",
      "count": 3,
      "review_ids": [
        "89742",
        "96802",
        "89931"
      ],
      "samples": []
    },
    {
      "word": "반품",
      "type": "complaint",
      "count": 4,
      "review_ids": [
        "89742",
        "89782",
        "89931",
        "96774"
      ],
      "samples": []
    },
    {
      "word": "세탁",
      "type": "improvement",
      "count": 3,
      "review_ids": [
        "96818",
        "96616",
        "89857"
      ],
      "samples": []
    },
    {
      "word": "가격",
      "type": "complaint",
      "count": 2,
      "review_ids": [
        "89898",
        "96802"
      ],
      "samples": []
    }
  ],
  "analyzed_total": 59,
  "batches": {
    "total": 2,
    "ok": 2
  }
}